adbhelper/__init__.py
adbhelper/cli.py
adbhelper/commands/__init__.py
adbhelper/commands/app_commands.py
adbhelper/commands/capture_commands.py
adbhelper/commands/log_commands.py
adbhelper/commands/register.py
adbhelper/commands/utils.py
adbhelper/core/__init__.py
adbhelper/core/adb.py
adbhelper/core/connection_history.py
adbhelper/core/device.py
adbhelper/core/mdns_discovery.py
adbhelper/core/mdns_pairing.py
adbhelper/core/pairing.py
adbhelper/core/spake2_pairing.py
adbhelper/features/__init__.py
adbhelper/scripts/__init__.py
adbhelper/scripts/enable_adb_helper.py
adbhelper/utils/__init__.py
adbh-0.1.1.dist-info/METADATA
adbh-0.1.1.dist-info/WHEEL
adbh-0.1.1.dist-info/entry_points.txt
adbh-0.1.1.dist-info/top_level.txt
adbh-0.1.1.dist-info/RECORD
