Metadata-Version: 2.4
Name: adbh
Version: 0.1.1
Summary: A cross-platform ADB helper tool for Android device management
Home-page: https://github.com/mattintech/adbhelper
Author: Matt Hills
Author-email: Your Name <mattintech@gmail.com>
Maintainer-email: Your Name <mattintech@gmail.com>
License-Expression: MIT
Project-URL: Homepage, https://github.com/mattintech/adbhelper
Project-URL: Documentation, https://github.com/mattintech/adbhelper#readme
Project-URL: Repository, https://github.com/mattintech/adbhelper.git
Project-URL: Bug Tracker, https://github.com/mattintech/adbhelper/issues
Keywords: adb,android,debugging,development,tools
Classifier: Development Status :: 3 - Alpha
Classifier: Intended Audience :: Developers
Classifier: Topic :: Software Development :: Build Tools
Classifier: Topic :: Software Development :: Debuggers
Classifier: Topic :: System :: Shells
Classifier: Programming Language :: Python :: 3
Classifier: Programming Language :: Python :: 3.8
Classifier: Programming Language :: Python :: 3.9
Classifier: Programming Language :: Python :: 3.10
Classifier: Programming Language :: Python :: 3.11
Classifier: Programming Language :: Python :: 3.12
Classifier: Operating System :: OS Independent
Classifier: Environment :: Console
Requires-Python: >=3.8
Requires-Dist: click>=8.1.0
Requires-Dist: rich>=13.0.0
Requires-Dist: pyyaml>=6.0
Requires-Dist: psutil>=5.9.0
Requires-Dist: watchdog>=3.0.0
Requires-Dist: qrcode[pil]>=7.4.0
Requires-Dist: zeroconf>=0.131.0
Requires-Dist: spake2>=0.8
Requires-Dist: cryptography>=41.0.0
Provides-Extra: dev
Requires-Dist: pytest>=7.0.0; extra == "dev"
Requires-Dist: pytest-cov>=4.0.0; extra == "dev"
Requires-Dist: black>=23.0.0; extra == "dev"
Requires-Dist: ruff>=0.1.0; extra == "dev"
Requires-Dist: mypy>=1.0.0; extra == "dev"
Dynamic: author
Dynamic: home-page
Dynamic: requires-python
